monkdb_langchain/__init__.py
monkdb_langchain/caching.py
monkdb_langchain/data_loaders.py
monkdb_langchain/doc_retrievers.py
monkdb_langchain/patches.py
monkdb_langchain/store_chat.py
monkdb_langchain/vector_datastores/__init__.py
monkdb_langchain/vector_datastores/main.py
monkdb_langchain/vector_datastores/multi_collections.py
monkdb_langchain/vector_datastores/sa_models.py
monkdb_langchain-0.1.2.dist-info/LICENSE
monkdb_langchain-0.1.2.dist-info/METADATA
monkdb_langchain-0.1.2.dist-info/WHEEL
monkdb_langchain-0.1.2.dist-info/RECORD
